Metadata-Version: 2.4
Name: anyspecs
Version: 0.0.5
Summary: Specs Export Tool for AI Assistants
Author-email: AnySpecs Team <me@timerring.com>
Maintainer-email: AnySpecs Team <me@timerring.com>
License:                                  Apache License
Project-URL: Homepage, https://github.com/anyspecs/anyspecs-cli
Project-URL: Documentation, https://github.com/anyspecs/anyspecs-cli/wiki
Project-URL: Repository, https://github.com/anyspecs/anyspecs-cli.git
Project-URL: Bug Tracker, https://github.com/anyspecs/anyspecs-cli/issues
Project-URL: Changelog, https://github.com/anyspecs/anyspecs-cli/blob/main/CHANGELOG.md
Keywords: chat,export,ai,assistant,cursor,claude,history,backup,markdown,html,json
Classifier: Programming Language :: Python :: 3
Classifier: Programming Language :: Python :: 3.8
Classifier: Programming Language :: Python :: 3.9
Classifier: Programming Language :: Python :: 3.10
Classifier: Programming Language :: Python :: 3.11
Classifier: Programming Language :: Python :: 3.12
Classifier: Operating System :: OS Independent
Classifier: Environment :: Console
Requires-Python: >=3.8
License-File: LICENSE
Requires-Dist: requests>=2.25.0
Requires-Dist: python-dateutil>=2.8.0
Requires-Dist: pathlib2>=2.3.0
Provides-Extra: dev
Requires-Dist: pytest>=6.0; extra == "dev"
Requires-Dist: pytest-cov>=2.0; extra == "dev"
Requires-Dist: black>=21.0; extra == "dev"
Requires-Dist: flake8>=3.8; extra == "dev"
Requires-Dist: mypy>=0.800; extra == "dev"
Requires-Dist: pre-commit>=2.0; extra == "dev"
Provides-Extra: rich
Requires-Dist: rich>=13.0.0; extra == "rich"
Provides-Extra: test
Requires-Dist: pytest>=6.0; extra == "test"
Requires-Dist: pytest-cov>=2.0; extra == "test"
Requires-Dist: pytest-mock>=3.0; extra == "test"
Dynamic: license-file
